odoo/addons/website_sale_partner_second_lastname/README.rst
odoo/addons/website_sale_partner_second_lastname/__init__.py
odoo/addons/website_sale_partner_second_lastname/__manifest__.py
odoo/addons/website_sale_partner_second_lastname/controllers/__init__.py
odoo/addons/website_sale_partner_second_lastname/controllers/main.py
odoo/addons/website_sale_partner_second_lastname/controllers/portal.py
odoo/addons/website_sale_partner_second_lastname/i18n/es.po
odoo/addons/website_sale_partner_second_lastname/models/__init__.py
odoo/addons/website_sale_partner_second_lastname/models/res_partner.py
odoo/addons/website_sale_partner_second_lastname/models/res_users.py
odoo/addons/website_sale_partner_second_lastname/static/description/icon.png
odoo/addons/website_sale_partner_second_lastname/views/auth_signup_login_templates.xml
odoo/addons/website_sale_partner_second_lastname/views/portal_templates.xml
odoo/addons/website_sale_partner_second_lastname/views/templates.xml
odoo_addon_website_sale_partner_second_lastname-15.0.1.0.0.4.dist-info/METADATA
odoo_addon_website_sale_partner_second_lastname-15.0.1.0.0.4.dist-info/WHEEL
odoo_addon_website_sale_partner_second_lastname-15.0.1.0.0.4.dist-info/top_level.txt
odoo_addon_website_sale_partner_second_lastname-15.0.1.0.0.4.dist-info/RECORD
