Metadata-Version: 2.1
Name: odoo-addon-website_sale_partner_second_lastname
Version: 15.0.1.0.0.4
Requires-Python: >=3.8
Requires-Dist: odoo-addon-partner_second_lastname>=15.0dev,<15.1dev
Requires-Dist: odoo-addon-website_sale_partner_firstname>=15.0dev,<15.1dev
Requires-Dist: odoo>=15.0a,<15.1dev
Summary: Introduce second lastname in website.
Home-page: https://github.com/sygel-technology/sy-website
License: AGPL-3
Author: Sygel, Odoo Community Association (OCA)
Author-email: support@odoo-community.org
Classifier: Programming Language :: Python
Classifier: Framework :: Odoo
Classifier: Framework :: Odoo :: 15.0
Classifier: License :: OSI Approved :: GNU Affero General Public License v3
Classifier: Development Status :: 4 - Beta
